{
    "export_type": "race",
    "championship_name": "NYE Series",
    "season_id": "series_6",
    "season_name": "",
    "race_id": "220",
    "race_name": "R12 - Australia",
    "round": 12,
    "date": "",
    "track": "Melbourne",
    "fastest_lap_driver": "Ulises",
    "fastest_lap_driver_id": "driver_mtsfrg",
    "dotd_driver": "",
    "dotd_driver_id": "",
    "results": [
        {
            "driver_id": "driver_mtsfrg",
            "name": "MTSFRG",
            "team": "Haas",
            "position": 1,
            "points": 78.0,
            "status": "",
            "best_lap": "",
            "best_lap_sec": "",
            "total_time": "",
            "total_time_sec": "",
            "time_gap": "",
            "penalty_time": "",
            "total_incidents": 0,
            "laps": [],
            "events": []
        },
        {
            "driver_id": "driver_sz_angel",
            "name": "Sz Angel",
            "team": "Mercedes",
            "position": 2,
            "points": 54.0,
            "status": "",
            "best_lap": "",
            "best_lap_sec": "",
            "total_time": "",
            "total_time_sec": "",
            "time_gap": "",
            "penalty_time": "",
            "total_incidents": 0,
            "laps": [],
            "events": []
        },
        {
            "driver_id": "driver_leozever",
            "name": "Leozever",
            "team": "Williams",
            "position": 3,
            "points": 45.0,
            "status": "",
            "best_lap": "",
            "best_lap_sec": "",
            "total_time": "",
            "total_time_sec": "",
            "time_gap": "",
            "penalty_time": "",
            "total_incidents": 0,
            "laps": [],
            "events": []
        },
        {
            "driver_id": "driver_memingow",
            "name": "Memingow",
            "team": "Red Bull",
            "position": 4,
            "points": 36.0,
            "status": "",
            "best_lap": "",
            "best_lap_sec": "",
            "total_time": "",
            "total_time_sec": "",
            "time_gap": "",
            "penalty_time": "",
            "total_incidents": 0,
            "laps": [],
            "events": []
        },
        {
            "driver_id": "driver_gabrielb01",
            "name": "Gabriel.b01",
            "team": "Sauber",
            "position": 5,
            "points": 30.0,
            "status": "",
            "best_lap": "",
            "best_lap_sec": "",
            "total_time": "",
            "total_time_sec": "",
            "time_gap": "",
            "penalty_time": "",
            "total_incidents": 0,
            "laps": [],
            "events": []
        },
        {
            "driver_id": "driver_puffy",
            "name": "HipAcorn",
            "team": "Haas",
            "position": 6,
            "points": 24.0,
            "status": "",
            "best_lap": "",
            "best_lap_sec": "",
            "total_time": "",
            "total_time_sec": "",
            "time_gap": "",
            "penalty_time": "",
            "total_incidents": 0,
            "laps": [],
            "events": []
        },
        {
            "driver_id": "driver_termopolio",
            "name": "Termopolio",
            "team": "Red Bull",
            "position": 7,
            "points": 18.0,
            "status": "",
            "best_lap": "",
            "best_lap_sec": "",
            "total_time": "",
            "total_time_sec": "",
            "time_gap": "",
            "penalty_time": "",
            "total_incidents": 0,
            "laps": [],
            "events": []
        },
        {
            "driver_id": "driver_sgc_lionel",
            "name": "SGC Lionel",
            "team": "Reserve Driver",
            "position": 8,
            "points": 12.0,
            "status": "",
            "best_lap": "",
            "best_lap_sec": "",
            "total_time": "",
            "total_time_sec": "",
            "time_gap": "",
            "penalty_time": "",
            "total_incidents": 0,
            "laps": [],
            "events": []
        },
        {
            "driver_id": "driver_siegerng",
            "name": "SiegerNG",
            "team": "Aston Martin",
            "position": 9,
            "points": 6.0,
            "status": "",
            "best_lap": "",
            "best_lap_sec": "",
            "total_time": "",
            "total_time_sec": "",
            "time_gap": "",
            "penalty_time": "",
            "total_incidents": 0,
            "laps": [],
            "events": []
        },
        {
            "driver_id": "driver_capisaurus",
            "name": "Capisaurus",
            "team": "Ferrari",
            "position": 10,
            "points": 3.0,
            "status": "",
            "best_lap": "",
            "best_lap_sec": "",
            "total_time": "",
            "total_time_sec": "",
            "time_gap": "",
            "penalty_time": "",
            "total_incidents": 0,
            "laps": [],
            "events": []
        }
    ],
    "sprint_results": [],
    "exported_at": "2026-02-07T21:14:46"
}