{
    "export_type": "season",
    "championship_name": "NyE Series",
    "season_id": "series_2",
    "season_name": "Series 2",
    "total_rounds": 18,
    "disputed_rounds": 18,
    "pending_rounds": 0,
    "races": [
        {
            "round": 1,
            "race_id": "140",
            "name": "R1 - Australia",
            "date": "",
            "track": "Australia",
            "planned": false,
            "winner": "Verstappen",
            "fastest_lap": "Verstappen",
            "dotd": "Schizain",
            "results": [
                {
                    "position": 1,
                    "driver": "Verstappen",
                    "driver_id": "verstappen",
                    "team": "AlphaTauri",
                    "points": 26.0,
                    "status": ""
                },
                {
                    "position": 2,
                    "driver": "MrPresident2004",
                    "driver_id": "mrpresident2004",
                    "team": "Ferrari",
                    "points": 18.0,
                    "status": ""
                },
                {
                    "position": 3,
                    "driver": "Schizain",
                    "driver_id": "schizain",
                    "team": "Reserva",
                    "points": 15.0,
                    "status": ""
                },
                {
                    "position": 4,
                    "driver": "Izquierdoxdd",
                    "driver_id": "izquierdoxdd",
                    "team": "Aston Martin",
                    "points": 12.0,
                    "status": ""
                },
                {
                    "position": 5,
                    "driver": "Gozark",
                    "driver_id": "gozark",
                    "team": "McLaren",
                    "points": 10.0,
                    "status": ""
                },
                {
                    "position": 6,
                    "driver": "Thiago",
                    "driver_id": "thiago",
                    "team": "Mercedes",
                    "points": 8.0,
                    "status": ""
                },
                {
                    "position": 7,
                    "driver": "Capisaurus",
                    "driver_id": "capisaurus",
                    "team": "Ferrari",
                    "points": 6.0,
                    "status": ""
                },
                {
                    "position": 8,
                    "driver": "AMZ Racing",
                    "driver_id": "amz_racing",
                    "team": "Alpine",
                    "points": 4.0,
                    "status": ""
                },
                {
                    "position": 9,
                    "driver": "Chuyto",
                    "driver_id": "chuyto",
                    "team": "Alfa Romeo",
                    "points": 2.0,
                    "status": ""
                },
                {
                    "position": 10,
                    "driver": "Memingow",
                    "driver_id": "memingow",
                    "team": "Aston Martin",
                    "points": 1.0,
                    "status": ""
                },
                {
                    "position": 12,
                    "driver": "Hector Zambrano",
                    "driver_id": "hector_zambrano",
                    "team": "Red Bull",
                    "points": 0.0,
                    "status": ""
                },
                {
                    "position": 13,
                    "driver": "MrSteveHyuga",
                    "driver_id": "mrstevehyuga",
                    "team": "Williams",
                    "points": 0.0,
                    "status": ""
                }
            ]
        },
        {
            "round": 2,
            "race_id": "141",
            "name": "R2 - Saudi Arabia",
            "date": "",
            "track": "Saudi Arabia",
            "planned": false,
            "winner": "AMZ Racing",
            "fastest_lap": "AMZ Racing",
            "dotd": "NoSoyYo98",
            "results": [
                {
                    "position": 1,
                    "driver": "AMZ Racing",
                    "driver_id": "amz_racing",
                    "team": "Alpine",
                    "points": 26.0,
                    "status": ""
                },
                {
                    "position": 2,
                    "driver": "NoSoyYo98",
                    "driver_id": "nosoyyo98",
                    "team": "Mercedes",
                    "points": 18.0,
                    "status": ""
                },
                {
                    "position": 3,
                    "driver": "MrPresident2004",
                    "driver_id": "mrpresident2004",
                    "team": "Ferrari",
                    "points": 15.0,
                    "status": ""
                },
                {
                    "position": 4,
                    "driver": "Memingow",
                    "driver_id": "memingow",
                    "team": "Aston Martin",
                    "points": 12.0,
                    "status": ""
                },
                {
                    "position": 5,
                    "driver": "Hector Zambrano",
                    "driver_id": "hector_zambrano",
                    "team": "Red Bull",
                    "points": 10.0,
                    "status": ""
                },
                {
                    "position": 6,
                    "driver": "Gozark",
                    "driver_id": "gozark",
                    "team": "McLaren",
                    "points": 8.0,
                    "status": ""
                },
                {
                    "position": 7,
                    "driver": "Thiago",
                    "driver_id": "thiago",
                    "team": "Mercedes",
                    "points": 6.0,
                    "status": ""
                },
                {
                    "position": 8,
                    "driver": "Verstappen",
                    "driver_id": "verstappen",
                    "team": "AlphaTauri",
                    "points": 4.0,
                    "status": ""
                },
                {
                    "position": 9,
                    "driver": "Chuyto",
                    "driver_id": "chuyto",
                    "team": "Alfa Romeo",
                    "points": 2.0,
                    "status": ""
                },
                {
                    "position": 10,
                    "driver": "SteelWarrior",
                    "driver_id": "steelwarrior",
                    "team": "McLaren",
                    "points": 1.0,
                    "status": ""
                },
                {
                    "position": 11,
                    "driver": "Capisaurus",
                    "driver_id": "capisaurus",
                    "team": "Ferrari",
                    "points": 0.0,
                    "status": ""
                },
                {
                    "position": 11,
                    "driver": "AlexMatrix266",
                    "driver_id": "alexmatrix266",
                    "team": "Williams",
                    "points": 0.0,
                    "status": ""
                },
                {
                    "position": 12,
                    "driver": "Victor xd",
                    "driver_id": "victor_xd",
                    "team": "Alpine",
                    "points": 0.0,
                    "status": ""
                },
                {
                    "position": 13,
                    "driver": "Izquierdoxdd",
                    "driver_id": "izquierdoxdd",
                    "team": "Aston Martin",
                    "points": 0.0,
                    "status": ""
                },
                {
                    "position": 14,
                    "driver": "Drasticalrose",
                    "driver_id": "drasticalrose",
                    "team": "Ferrari",
                    "points": 0.0,
                    "status": ""
                }
            ]
        },
        {
            "round": 3,
            "race_id": "142",
            "name": "R3 - Great Britain",
            "date": "",
            "track": "Great Britain",
            "planned": false,
            "winner": "Gozark",
            "fastest_lap": "Gozark",
            "dotd": "",
            "results": [
                {
                    "position": 1,
                    "driver": "Gozark",
                    "driver_id": "gozark",
                    "team": "McLaren",
                    "points": 26.0,
                    "status": ""
                },
                {
                    "position": 2,
                    "driver": "MrPresident2004",
                    "driver_id": "mrpresident2004",
                    "team": "Ferrari",
                    "points": 18.0,
                    "status": ""
                },
                {
                    "position": 3,
                    "driver": "Izquierdoxdd",
                    "driver_id": "izquierdoxdd",
                    "team": "Aston Martin",
                    "points": 15.0,
                    "status": ""
                },
                {
                    "position": 4,
                    "driver": "Memingow",
                    "driver_id": "memingow",
                    "team": "Aston Martin",
                    "points": 12.0,
                    "status": ""
                },
                {
                    "position": 5,
                    "driver": "Thiago",
                    "driver_id": "thiago",
                    "team": "Mercedes",
                    "points": 10.0,
                    "status": ""
                },
                {
                    "position": 6,
                    "driver": "Capisaurus",
                    "driver_id": "capisaurus",
                    "team": "Ferrari",
                    "points": 8.0,
                    "status": ""
                },
                {
                    "position": 7,
                    "driver": "Hector Zambrano",
                    "driver_id": "hector_zambrano",
                    "team": "Red Bull",
                    "points": 6.0,
                    "status": "DNF"
                },
                {
                    "position": 8,
                    "driver": "Victor xd",
                    "driver_id": "victor_xd",
                    "team": "Alpine",
                    "points": 4.0,
                    "status": "DNF"
                },
                {
                    "position": 9,
                    "driver": "Chuyto",
                    "driver_id": "chuyto",
                    "team": "Alfa Romeo",
                    "points": 2.0,
                    "status": "DNF"
                }
            ]
        },
        {
            "round": 4,
            "race_id": "143",
            "name": "R4 - Austria",
            "date": "",
            "track": "",
            "planned": false,
            "winner": "NoSoyYo98",
            "fastest_lap": "Antonio GC",
            "dotd": "",
            "results": [
                {
                    "position": 1,
                    "driver": "NoSoyYo98",
                    "driver_id": "nosoyyo98",
                    "team": "Mercedes",
                    "points": 25.0,
                    "status": ""
                },
                {
                    "position": 2,
                    "driver": "MrPresident2004",
                    "driver_id": "mrpresident2004",
                    "team": "Ferrari",
                    "points": 18.0,
                    "status": ""
                },
                {
                    "position": 3,
                    "driver": "Izquierdoxdd",
                    "driver_id": "izquierdoxdd",
                    "team": "Aston Martin",
                    "points": 15.0,
                    "status": ""
                },
                {
                    "position": 4,
                    "driver": "Victor xd",
                    "driver_id": "victor_xd",
                    "team": "Alpine",
                    "points": 12.0,
                    "status": ""
                },
                {
                    "position": 5,
                    "driver": "Memingow",
                    "driver_id": "memingow",
                    "team": "Aston Martin",
                    "points": 10.0,
                    "status": ""
                },
                {
                    "position": 6,
                    "driver": "Chuyto",
                    "driver_id": "chuyto",
                    "team": "Alfa Romeo",
                    "points": 8.0,
                    "status": ""
                },
                {
                    "position": 7,
                    "driver": "Antonio GC",
                    "driver_id": "antonio_gc",
                    "team": "Red Bull",
                    "points": 7.0,
                    "status": ""
                },
                {
                    "position": 8,
                    "driver": "Thiago",
                    "driver_id": "thiago",
                    "team": "Mercedes",
                    "points": 4.0,
                    "status": ""
                },
                {
                    "position": 9,
                    "driver": "Verstappen",
                    "driver_id": "verstappen",
                    "team": "AlphaTauri",
                    "points": 2.0,
                    "status": ""
                },
                {
                    "position": 10,
                    "driver": "Capisaurus",
                    "driver_id": "capisaurus",
                    "team": "Ferrari",
                    "points": 1.0,
                    "status": ""
                },
                {
                    "position": 11,
                    "driver": "Hector Zambrano",
                    "driver_id": "hector_zambrano",
                    "team": "Red Bull",
                    "points": 0.0,
                    "status": ""
                },
                {
                    "position": 12,
                    "driver": "RubyCrayfish",
                    "driver_id": "rubycrayfish",
                    "team": "Ferrari",
                    "points": 0.0,
                    "status": ""
                }
            ]
        },
        {
            "round": 5,
            "race_id": "144",
            "name": "R5 - Las Vegas",
            "date": "",
            "track": "",
            "planned": false,
            "winner": "AMZ Racing",
            "fastest_lap": "NoSoyYo98",
            "dotd": "AMZ Racing",
            "results": [
                {
                    "position": 1,
                    "driver": "AMZ Racing",
                    "driver_id": "amz_racing",
                    "team": "Alpine",
                    "points": 25.0,
                    "status": ""
                },
                {
                    "position": 2,
                    "driver": "NoSoyYo98",
                    "driver_id": "nosoyyo98",
                    "team": "Mercedes",
                    "points": 19.0,
                    "status": ""
                },
                {
                    "position": 3,
                    "driver": "Izquierdoxdd",
                    "driver_id": "izquierdoxdd",
                    "team": "Aston Martin",
                    "points": 15.0,
                    "status": ""
                },
                {
                    "position": 4,
                    "driver": "Memingow",
                    "driver_id": "memingow",
                    "team": "Aston Martin",
                    "points": 12.0,
                    "status": ""
                },
                {
                    "position": 5,
                    "driver": "Victor xd",
                    "driver_id": "victor_xd",
                    "team": "Alpine",
                    "points": 10.0,
                    "status": ""
                },
                {
                    "position": 6,
                    "driver": "MrPresident2004",
                    "driver_id": "mrpresident2004",
                    "team": "Ferrari",
                    "points": 8.0,
                    "status": ""
                },
                {
                    "position": 7,
                    "driver": "Gozark",
                    "driver_id": "gozark",
                    "team": "McLaren",
                    "points": 6.0,
                    "status": ""
                },
                {
                    "position": 8,
                    "driver": "Capisaurus",
                    "driver_id": "capisaurus",
                    "team": "Ferrari",
                    "points": 4.0,
                    "status": ""
                },
                {
                    "position": 9,
                    "driver": "Chuyto",
                    "driver_id": "chuyto",
                    "team": "Alfa Romeo",
                    "points": 2.0,
                    "status": ""
                }
            ]
        },
        {
            "round": 6,
            "race_id": "145",
            "name": "R6 - Bahrain",
            "date": "",
            "track": "Bahrain",
            "planned": false,
            "winner": "AMZ Racing",
            "fastest_lap": "AMZ Racing",
            "dotd": "",
            "results": [
                {
                    "position": 1,
                    "driver": "AMZ Racing",
                    "driver_id": "amz_racing",
                    "team": "Alpine",
                    "points": 26.0,
                    "status": ""
                },
                {
                    "position": 2,
                    "driver": "Gozark",
                    "driver_id": "gozark",
                    "team": "McLaren",
                    "points": 18.0,
                    "status": ""
                },
                {
                    "position": 3,
                    "driver": "Izquierdoxdd",
                    "driver_id": "izquierdoxdd",
                    "team": "Aston Martin",
                    "points": 15.0,
                    "status": ""
                },
                {
                    "position": 4,
                    "driver": "Victor xd",
                    "driver_id": "victor_xd",
                    "team": "Alpine",
                    "points": 12.0,
                    "status": ""
                },
                {
                    "position": 5,
                    "driver": "MrPresident2004",
                    "driver_id": "mrpresident2004",
                    "team": "Ferrari",
                    "points": 10.0,
                    "status": ""
                },
                {
                    "position": 6,
                    "driver": "NoSoyYo98",
                    "driver_id": "nosoyyo98",
                    "team": "Mercedes",
                    "points": 8.0,
                    "status": ""
                },
                {
                    "position": 7,
                    "driver": "Memingow",
                    "driver_id": "memingow",
                    "team": "Aston Martin",
                    "points": 6.0,
                    "status": ""
                },
                {
                    "position": 8,
                    "driver": "Thiago",
                    "driver_id": "thiago",
                    "team": "Mercedes",
                    "points": 4.0,
                    "status": ""
                },
                {
                    "position": 9,
                    "driver": "Capisaurus",
                    "driver_id": "capisaurus",
                    "team": "Ferrari",
                    "points": 2.0,
                    "status": ""
                },
                {
                    "position": 10,
                    "driver": "Yindaxmx",
                    "driver_id": "yindaxmx",
                    "team": "AlphaTauri",
                    "points": 1.0,
                    "status": ""
                },
                {
                    "position": 11,
                    "driver": "Chuyto",
                    "driver_id": "chuyto",
                    "team": "Alfa Romeo",
                    "points": 0.0,
                    "status": ""
                }
            ]
        },
        {
            "round": 7,
            "race_id": "146",
            "name": "R7 - Singapore",
            "date": "",
            "track": "Singapore",
            "planned": false,
            "winner": "MrPresident2004",
            "fastest_lap": "MrPresident2004",
            "dotd": "",
            "results": [
                {
                    "position": 1,
                    "driver": "MrPresident2004",
                    "driver_id": "mrpresident2004",
                    "team": "Ferrari",
                    "points": 26.0,
                    "status": ""
                },
                {
                    "position": 2,
                    "driver": "Memingow",
                    "driver_id": "memingow",
                    "team": "Aston Martin",
                    "points": 18.0,
                    "status": ""
                },
                {
                    "position": 3,
                    "driver": "Izquierdoxdd",
                    "driver_id": "izquierdoxdd",
                    "team": "Aston Martin",
                    "points": 15.0,
                    "status": ""
                },
                {
                    "position": 5,
                    "driver": "Thiago",
                    "driver_id": "thiago",
                    "team": "Mercedes",
                    "points": 10.0,
                    "status": ""
                },
                {
                    "position": 6,
                    "driver": "Yindaxmx",
                    "driver_id": "yindaxmx",
                    "team": "AlphaTauri",
                    "points": 8.0,
                    "status": ""
                },
                {
                    "position": 7,
                    "driver": "Capisaurus",
                    "driver_id": "capisaurus",
                    "team": "Ferrari",
                    "points": 6.0,
                    "status": "DNF"
                },
                {
                    "position": 8,
                    "driver": "Gozark",
                    "driver_id": "gozark",
                    "team": "McLaren",
                    "points": 4.0,
                    "status": "DNF"
                }
            ]
        },
        {
            "round": 8,
            "race_id": "147",
            "name": "R8 - Mexico",
            "date": "",
            "track": "Mexico",
            "planned": false,
            "winner": "MrPresident2004",
            "fastest_lap": "NoSoyYo98",
            "dotd": "",
            "results": [
                {
                    "position": 1,
                    "driver": "MrPresident2004",
                    "driver_id": "mrpresident2004",
                    "team": "Ferrari",
                    "points": 25.0,
                    "status": ""
                },
                {
                    "position": 2,
                    "driver": "Izquierdoxdd",
                    "driver_id": "izquierdoxdd",
                    "team": "Aston Martin",
                    "points": 18.0,
                    "status": ""
                },
                {
                    "position": 3,
                    "driver": "Thiago",
                    "driver_id": "thiago",
                    "team": "Mercedes",
                    "points": 15.0,
                    "status": ""
                },
                {
                    "position": 4,
                    "driver": "Hector Zambrano",
                    "driver_id": "hector_zambrano",
                    "team": "Red Bull",
                    "points": 12.0,
                    "status": ""
                },
                {
                    "position": 4,
                    "driver": "Seb",
                    "driver_id": "seb",
                    "team": "AlphaTauri",
                    "points": 12.0,
                    "status": ""
                },
                {
                    "position": 5,
                    "driver": "NoSoyYo98",
                    "driver_id": "nosoyyo98",
                    "team": "Mercedes",
                    "points": 11.0,
                    "status": ""
                },
                {
                    "position": 6,
                    "driver": "Capisaurus",
                    "driver_id": "capisaurus",
                    "team": "Ferrari",
                    "points": 8.0,
                    "status": ""
                },
                {
                    "position": 7,
                    "driver": "Memingow",
                    "driver_id": "memingow",
                    "team": "Aston Martin",
                    "points": 6.0,
                    "status": ""
                },
                {
                    "position": 8,
                    "driver": "Victor xd",
                    "driver_id": "victor_xd",
                    "team": "Alpine",
                    "points": 4.0,
                    "status": ""
                }
            ]
        },
        {
            "round": 9,
            "race_id": "148",
            "name": "R9 - Belgium",
            "date": "",
            "track": "Belgium",
            "planned": false,
            "winner": "NoSoyYo98",
            "fastest_lap": "NoSoyYo98",
            "dotd": "Thiago",
            "results": [
                {
                    "position": 1,
                    "driver": "NoSoyYo98",
                    "driver_id": "nosoyyo98",
                    "team": "Mercedes",
                    "points": 26.0,
                    "status": ""
                },
                {
                    "position": 2,
                    "driver": "MrSteveHyuga",
                    "driver_id": "mrstevehyuga",
                    "team": "Williams",
                    "points": 18.0,
                    "status": ""
                },
                {
                    "position": 3,
                    "driver": "MrPresident2004",
                    "driver_id": "mrpresident2004",
                    "team": "Ferrari",
                    "points": 15.0,
                    "status": ""
                },
                {
                    "position": 4,
                    "driver": "Memingow",
                    "driver_id": "memingow",
                    "team": "Aston Martin",
                    "points": 12.0,
                    "status": ""
                },
                {
                    "position": 5,
                    "driver": "Thiago",
                    "driver_id": "thiago",
                    "team": "Mercedes",
                    "points": 10.0,
                    "status": ""
                },
                {
                    "position": 6,
                    "driver": "Izquierdoxdd",
                    "driver_id": "izquierdoxdd",
                    "team": "Aston Martin",
                    "points": 8.0,
                    "status": ""
                },
                {
                    "position": 7,
                    "driver": "Yindaxmx",
                    "driver_id": "yindaxmx",
                    "team": "AlphaTauri",
                    "points": 6.0,
                    "status": ""
                },
                {
                    "position": 8,
                    "driver": "Hector Zambrano",
                    "driver_id": "hector_zambrano",
                    "team": "Red Bull",
                    "points": 4.0,
                    "status": ""
                },
                {
                    "position": 9,
                    "driver": "Capisaurus",
                    "driver_id": "capisaurus",
                    "team": "Ferrari",
                    "points": 2.0,
                    "status": ""
                }
            ]
        },
        {
            "round": 10,
            "race_id": "149",
            "name": "R10 - Japan",
            "date": "",
            "track": "Japan",
            "planned": false,
            "winner": "Izquierdoxdd",
            "fastest_lap": "Gozark",
            "dotd": "Gozark",
            "results": [
                {
                    "position": 1,
                    "driver": "Izquierdoxdd",
                    "driver_id": "izquierdoxdd",
                    "team": "Aston Martin",
                    "points": 25.0,
                    "status": ""
                },
                {
                    "position": 2,
                    "driver": "Gozark",
                    "driver_id": "gozark",
                    "team": "McLaren",
                    "points": 19.0,
                    "status": ""
                },
                {
                    "position": 3,
                    "driver": "MrPresident2004",
                    "driver_id": "mrpresident2004",
                    "team": "Ferrari",
                    "points": 15.0,
                    "status": ""
                },
                {
                    "position": 5,
                    "driver": "Memingow",
                    "driver_id": "memingow",
                    "team": "Aston Martin",
                    "points": 10.0,
                    "status": ""
                },
                {
                    "position": 6,
                    "driver": "Yindaxmx",
                    "driver_id": "yindaxmx",
                    "team": "AlphaTauri",
                    "points": 8.0,
                    "status": ""
                },
                {
                    "position": 7,
                    "driver": "Capisaurus",
                    "driver_id": "capisaurus",
                    "team": "Ferrari",
                    "points": 6.0,
                    "status": ""
                },
                {
                    "position": 8,
                    "driver": "Hector Zambrano",
                    "driver_id": "hector_zambrano",
                    "team": "Red Bull",
                    "points": 4.0,
                    "status": "DNF"
                }
            ]
        },
        {
            "round": 11,
            "race_id": "150",
            "name": "R11 - Qatar",
            "date": "",
            "track": "Qatar",
            "planned": false,
            "winner": "ElGast",
            "fastest_lap": "ElGast",
            "dotd": "Memingow",
            "results": [
                {
                    "position": 1,
                    "driver": "ElGast",
                    "driver_id": "elgast",
                    "team": "Reserva",
                    "points": 26.0,
                    "status": ""
                },
                {
                    "position": 2,
                    "driver": "Memingow",
                    "driver_id": "memingow",
                    "team": "Aston Martin",
                    "points": 18.0,
                    "status": ""
                },
                {
                    "position": 4,
                    "driver": "MrPresident2004",
                    "driver_id": "mrpresident2004",
                    "team": "Ferrari",
                    "points": 12.0,
                    "status": ""
                },
                {
                    "position": 4,
                    "driver": "HarryH",
                    "driver_id": "harryh",
                    "team": "Reserva",
                    "points": 12.0,
                    "status": ""
                },
                {
                    "position": 5,
                    "driver": "Izquierdoxdd",
                    "driver_id": "izquierdoxdd",
                    "team": "Aston Martin",
                    "points": 10.0,
                    "status": ""
                },
                {
                    "position": 6,
                    "driver": "Capisaurus",
                    "driver_id": "capisaurus",
                    "team": "Ferrari",
                    "points": 8.0,
                    "status": ""
                },
                {
                    "position": 7,
                    "driver": "Yindaxmx",
                    "driver_id": "yindaxmx",
                    "team": "AlphaTauri",
                    "points": 6.0,
                    "status": ""
                },
                {
                    "position": 8,
                    "driver": "Hector Zambrano",
                    "driver_id": "hector_zambrano",
                    "team": "Red Bull",
                    "points": 4.0,
                    "status": ""
                }
            ]
        },
        {
            "round": 12,
            "race_id": "151",
            "name": "R12 - Italia",
            "date": "",
            "track": "Monza",
            "planned": false,
            "winner": "ElGast",
            "fastest_lap": "ElGast",
            "dotd": "",
            "results": [
                {
                    "position": 1,
                    "driver": "ElGast",
                    "driver_id": "elgast",
                    "team": "Reserva",
                    "points": 26.0,
                    "status": ""
                },
                {
                    "position": 2,
                    "driver": "MrPresident2004",
                    "driver_id": "mrpresident2004",
                    "team": "Ferrari",
                    "points": 18.0,
                    "status": ""
                },
                {
                    "position": 2,
                    "driver": "NoSoyYo98",
                    "driver_id": "nosoyyo98",
                    "team": "Mercedes",
                    "points": 18.0,
                    "status": ""
                },
                {
                    "position": 3,
                    "driver": "Thiago",
                    "driver_id": "thiago",
                    "team": "Mercedes",
                    "points": 15.0,
                    "status": ""
                },
                {
                    "position": 3,
                    "driver": "HarryH",
                    "driver_id": "harryh",
                    "team": "Reserva",
                    "points": 15.0,
                    "status": ""
                },
                {
                    "position": 4,
                    "driver": "Capisaurus",
                    "driver_id": "capisaurus",
                    "team": "Ferrari",
                    "points": 12.0,
                    "status": ""
                },
                {
                    "position": 5,
                    "driver": "Memingow",
                    "driver_id": "memingow",
                    "team": "Aston Martin",
                    "points": 10.0,
                    "status": ""
                },
                {
                    "position": 6,
                    "driver": "Hector Zambrano",
                    "driver_id": "hector_zambrano",
                    "team": "Red Bull",
                    "points": 8.0,
                    "status": ""
                },
                {
                    "position": 7,
                    "driver": "Yindaxmx",
                    "driver_id": "yindaxmx",
                    "team": "AlphaTauri",
                    "points": 6.0,
                    "status": ""
                }
            ]
        },
        {
            "round": 13,
            "race_id": "152",
            "name": "R13 - Brazil",
            "date": "",
            "track": "Brazil",
            "planned": false,
            "winner": "",
            "fastest_lap": "MrPresident2004",
            "dotd": "",
            "results": [
                {
                    "position": 3,
                    "driver": "Izquierdoxdd",
                    "driver_id": "izquierdoxdd",
                    "team": "Aston Martin",
                    "points": 22.5,
                    "status": ""
                },
                {
                    "position": 4,
                    "driver": "Hector Zambrano",
                    "driver_id": "hector_zambrano",
                    "team": "Red Bull",
                    "points": 18.0,
                    "status": ""
                },
                {
                    "position": 5,
                    "driver": "MrPresident2004",
                    "driver_id": "mrpresident2004",
                    "team": "Ferrari",
                    "points": 16.5,
                    "status": ""
                },
                {
                    "position": 5,
                    "driver": "Yindaxmx",
                    "driver_id": "yindaxmx",
                    "team": "AlphaTauri",
                    "points": 15.0,
                    "status": ""
                },
                {
                    "position": 6,
                    "driver": "Capisaurus",
                    "driver_id": "capisaurus",
                    "team": "Ferrari",
                    "points": 12.0,
                    "status": ""
                },
                {
                    "position": 8,
                    "driver": "Thiago",
                    "driver_id": "thiago",
                    "team": "Mercedes",
                    "points": 6.0,
                    "status": ""
                },
                {
                    "position": 9,
                    "driver": "Memingow",
                    "driver_id": "memingow",
                    "team": "Aston Martin",
                    "points": 3.0,
                    "status": ""
                }
            ]
        },
        {
            "round": 14,
            "race_id": "153",
            "name": "R14 - Abu Dhabi",
            "date": "",
            "track": "Abu Dhabi",
            "planned": false,
            "winner": "MrPresident2004",
            "fastest_lap": "MrPresident2004",
            "dotd": "",
            "results": [
                {
                    "position": 1,
                    "driver": "MrPresident2004",
                    "driver_id": "mrpresident2004",
                    "team": "Ferrari",
                    "points": 26.0,
                    "status": ""
                },
                {
                    "position": 1,
                    "driver": "HarryH",
                    "driver_id": "harryh",
                    "team": "Reserva",
                    "points": 25.0,
                    "status": ""
                },
                {
                    "position": 2,
                    "driver": "Memingow",
                    "driver_id": "memingow",
                    "team": "Aston Martin",
                    "points": 18.0,
                    "status": ""
                },
                {
                    "position": 3,
                    "driver": "Izquierdoxdd",
                    "driver_id": "izquierdoxdd",
                    "team": "Aston Martin",
                    "points": 15.0,
                    "status": ""
                },
                {
                    "position": 4,
                    "driver": "NoSoyYo98",
                    "driver_id": "nosoyyo98",
                    "team": "Mercedes",
                    "points": 12.0,
                    "status": ""
                },
                {
                    "position": 4,
                    "driver": "Capisaurus",
                    "driver_id": "capisaurus",
                    "team": "Ferrari",
                    "points": 12.0,
                    "status": ""
                },
                {
                    "position": 6,
                    "driver": "Gozark",
                    "driver_id": "gozark",
                    "team": "McLaren",
                    "points": 8.0,
                    "status": ""
                },
                {
                    "position": 7,
                    "driver": "Thiago",
                    "driver_id": "thiago",
                    "team": "Mercedes",
                    "points": 6.0,
                    "status": ""
                }
            ]
        },
        {
            "round": 15,
            "race_id": "154",
            "name": "R15 - United States",
            "date": "",
            "track": "",
            "planned": false,
            "winner": "Thiago",
            "fastest_lap": "",
            "dotd": "",
            "results": [
                {
                    "position": 1,
                    "driver": "Thiago",
                    "driver_id": "thiago",
                    "team": "Mercedes",
                    "points": 25.0,
                    "status": ""
                },
                {
                    "position": 2,
                    "driver": "Memingow",
                    "driver_id": "memingow",
                    "team": "Aston Martin",
                    "points": 18.0,
                    "status": ""
                },
                {
                    "position": 3,
                    "driver": "MrPresident2004",
                    "driver_id": "mrpresident2004",
                    "team": "Ferrari",
                    "points": 15.0,
                    "status": ""
                },
                {
                    "position": 4,
                    "driver": "NoSoyYo98",
                    "driver_id": "nosoyyo98",
                    "team": "Mercedes",
                    "points": 12.0,
                    "status": ""
                },
                {
                    "position": 5,
                    "driver": "Hector Zambrano",
                    "driver_id": "hector_zambrano",
                    "team": "Red Bull",
                    "points": 10.0,
                    "status": ""
                },
                {
                    "position": 6,
                    "driver": "Izquierdoxdd",
                    "driver_id": "izquierdoxdd",
                    "team": "Aston Martin",
                    "points": 8.0,
                    "status": ""
                },
                {
                    "position": 7,
                    "driver": "Capisaurus",
                    "driver_id": "capisaurus",
                    "team": "Ferrari",
                    "points": 6.0,
                    "status": ""
                },
                {
                    "position": 8,
                    "driver": "Yindaxmx",
                    "driver_id": "yindaxmx",
                    "team": "AlphaTauri",
                    "points": 4.0,
                    "status": ""
                }
            ]
        },
        {
            "round": 16,
            "race_id": "155",
            "name": "R16 - Canada",
            "date": "",
            "track": "Canada",
            "planned": false,
            "winner": "Izquierdoxdd",
            "fastest_lap": "Thiago",
            "dotd": "",
            "results": [
                {
                    "position": 1,
                    "driver": "Izquierdoxdd",
                    "driver_id": "izquierdoxdd",
                    "team": "Aston Martin",
                    "points": 25.0,
                    "status": ""
                },
                {
                    "position": 2,
                    "driver": "Thiago",
                    "driver_id": "thiago",
                    "team": "Mercedes",
                    "points": 19.0,
                    "status": ""
                },
                {
                    "position": 3,
                    "driver": "MrPresident2004",
                    "driver_id": "mrpresident2004",
                    "team": "Ferrari",
                    "points": 15.0,
                    "status": ""
                },
                {
                    "position": 3,
                    "driver": "Yindaxmx",
                    "driver_id": "yindaxmx",
                    "team": "AlphaTauri",
                    "points": 15.0,
                    "status": ""
                },
                {
                    "position": 4,
                    "driver": "Memingow",
                    "driver_id": "memingow",
                    "team": "Aston Martin",
                    "points": 12.0,
                    "status": ""
                },
                {
                    "position": 5,
                    "driver": "Hector Zambrano",
                    "driver_id": "hector_zambrano",
                    "team": "Red Bull",
                    "points": 10.0,
                    "status": ""
                },
                {
                    "position": 6,
                    "driver": "Capisaurus",
                    "driver_id": "capisaurus",
                    "team": "Ferrari",
                    "points": 8.0,
                    "status": ""
                }
            ]
        },
        {
            "round": 17,
            "race_id": "156",
            "name": "R17 - Netherlands",
            "date": "",
            "track": "Netherlands",
            "planned": false,
            "winner": "Hector Zambrano",
            "fastest_lap": "MrPresident2004",
            "dotd": "",
            "results": [
                {
                    "position": 1,
                    "driver": "Hector Zambrano",
                    "driver_id": "hector_zambrano",
                    "team": "Red Bull",
                    "points": 25.0,
                    "status": ""
                },
                {
                    "position": 2,
                    "driver": "Capisaurus",
                    "driver_id": "capisaurus",
                    "team": "Ferrari",
                    "points": 18.0,
                    "status": ""
                },
                {
                    "position": 4,
                    "driver": "MrPresident2004",
                    "driver_id": "mrpresident2004",
                    "team": "Ferrari",
                    "points": 13.0,
                    "status": ""
                },
                {
                    "position": 5,
                    "driver": "Izquierdoxdd",
                    "driver_id": "izquierdoxdd",
                    "team": "Aston Martin",
                    "points": 10.0,
                    "status": ""
                },
                {
                    "position": 6,
                    "driver": "Memingow",
                    "driver_id": "memingow",
                    "team": "Aston Martin",
                    "points": 8.0,
                    "status": ""
                },
                {
                    "position": 6,
                    "driver": "Yindaxmx",
                    "driver_id": "yindaxmx",
                    "team": "AlphaTauri",
                    "points": 8.0,
                    "status": ""
                }
            ]
        },
        {
            "round": 18,
            "race_id": "157",
            "name": "R18 - Brazil",
            "date": "",
            "track": "",
            "planned": false,
            "winner": "Izquierdoxdd",
            "fastest_lap": "Izquierdoxdd",
            "dotd": "",
            "results": [
                {
                    "position": 1,
                    "driver": "Izquierdoxdd",
                    "driver_id": "izquierdoxdd",
                    "team": "Aston Martin",
                    "points": 39.0,
                    "status": ""
                },
                {
                    "position": 2,
                    "driver": "Thiago",
                    "driver_id": "thiago",
                    "team": "Mercedes",
                    "points": 27.0,
                    "status": ""
                },
                {
                    "position": 3,
                    "driver": "Capisaurus",
                    "driver_id": "capisaurus",
                    "team": "Ferrari",
                    "points": 22.5,
                    "status": ""
                },
                {
                    "position": 4,
                    "driver": "MrPresident2004",
                    "driver_id": "mrpresident2004",
                    "team": "Ferrari",
                    "points": 18.0,
                    "status": ""
                },
                {
                    "position": 5,
                    "driver": "HarryH",
                    "driver_id": "harryh",
                    "team": "Reserva",
                    "points": 15.0,
                    "status": ""
                },
                {
                    "position": 7,
                    "driver": "Hector Zambrano",
                    "driver_id": "hector_zambrano",
                    "team": "Red Bull",
                    "points": 9.0,
                    "status": ""
                },
                {
                    "position": 8,
                    "driver": "NoSoyYo98",
                    "driver_id": "nosoyyo98",
                    "team": "Mercedes",
                    "points": 6.0,
                    "status": ""
                },
                {
                    "position": 9,
                    "driver": "Memingow",
                    "driver_id": "memingow",
                    "team": "Aston Martin",
                    "points": 3.0,
                    "status": ""
                }
            ]
        }
    ],
    "drivers": [
        {
            "driver_id": "mrpresident2004",
            "name": "MrPresident2004",
            "number": "",
            "team": "Ferrari",
            "team_id": "team_ferrari",
            "total_points": 301.5,
            "rounds": {
                "1": {
                    "position": 2,
                    "points": 18.0,
                    "status": ""
                },
                "2": {
                    "position": 3,
                    "points": 15.0,
                    "status": ""
                },
                "3": {
                    "position": 2,
                    "points": 18.0,
                    "status": ""
                },
                "4": {
                    "position": 2,
                    "points": 18.0,
                    "status": ""
                },
                "5": {
                    "position": 6,
                    "points": 8.0,
                    "status": ""
                },
                "6": {
                    "position": 5,
                    "points": 10.0,
                    "status": ""
                },
                "7": {
                    "position": 1,
                    "points": 26.0,
                    "status": ""
                },
                "8": {
                    "position": 1,
                    "points": 25.0,
                    "status": ""
                },
                "9": {
                    "position": 3,
                    "points": 15.0,
                    "status": ""
                },
                "10": {
                    "position": 3,
                    "points": 15.0,
                    "status": ""
                },
                "11": {
                    "position": 4,
                    "points": 12.0,
                    "status": ""
                },
                "12": {
                    "position": 2,
                    "points": 18.0,
                    "status": ""
                },
                "13": {
                    "position": 5,
                    "points": 16.5,
                    "status": ""
                },
                "14": {
                    "position": 1,
                    "points": 26.0,
                    "status": ""
                },
                "15": {
                    "position": 3,
                    "points": 15.0,
                    "status": ""
                },
                "16": {
                    "position": 3,
                    "points": 15.0,
                    "status": ""
                },
                "17": {
                    "position": 4,
                    "points": 13.0,
                    "status": ""
                },
                "18": {
                    "position": 4,
                    "points": 18.0,
                    "status": ""
                }
            },
            "wins": 3,
            "sprint_wins": 0,
            "poles": 0,
            "podiums": 12,
            "fastest_laps": 4,
            "driver_of_the_day": 0
        },
        {
            "driver_id": "izquierdoxdd",
            "name": "Izquierdoxdd",
            "number": "",
            "team": "Aston Martin",
            "team_id": "team_aston_martin",
            "total_points": 267.5,
            "rounds": {
                "1": {
                    "position": 4,
                    "points": 12.0,
                    "status": ""
                },
                "2": {
                    "position": 13,
                    "points": 0.0,
                    "status": ""
                },
                "3": {
                    "position": 3,
                    "points": 15.0,
                    "status": ""
                },
                "4": {
                    "position": 3,
                    "points": 15.0,
                    "status": ""
                },
                "5": {
                    "position": 3,
                    "points": 15.0,
                    "status": ""
                },
                "6": {
                    "position": 3,
                    "points": 15.0,
                    "status": ""
                },
                "7": {
                    "position": 3,
                    "points": 15.0,
                    "status": ""
                },
                "8": {
                    "position": 2,
                    "points": 18.0,
                    "status": ""
                },
                "9": {
                    "position": 6,
                    "points": 8.0,
                    "status": ""
                },
                "10": {
                    "position": 1,
                    "points": 25.0,
                    "status": ""
                },
                "11": {
                    "position": 5,
                    "points": 10.0,
                    "status": ""
                },
                "13": {
                    "position": 3,
                    "points": 22.5,
                    "status": ""
                },
                "14": {
                    "position": 3,
                    "points": 15.0,
                    "status": ""
                },
                "15": {
                    "position": 6,
                    "points": 8.0,
                    "status": ""
                },
                "16": {
                    "position": 1,
                    "points": 25.0,
                    "status": ""
                },
                "17": {
                    "position": 5,
                    "points": 10.0,
                    "status": ""
                },
                "18": {
                    "position": 1,
                    "points": 39.0,
                    "status": ""
                }
            },
            "wins": 3,
            "sprint_wins": 0,
            "poles": 0,
            "podiums": 11,
            "fastest_laps": 1,
            "driver_of_the_day": 0
        },
        {
            "driver_id": "memingow",
            "name": "Memingow",
            "number": "",
            "team": "Aston Martin",
            "team_id": "team_aston_martin",
            "total_points": 189.0,
            "rounds": {
                "1": {
                    "position": 10,
                    "points": 1.0,
                    "status": ""
                },
                "2": {
                    "position": 4,
                    "points": 12.0,
                    "status": ""
                },
                "3": {
                    "position": 4,
                    "points": 12.0,
                    "status": ""
                },
                "4": {
                    "position": 5,
                    "points": 10.0,
                    "status": ""
                },
                "5": {
                    "position": 4,
                    "points": 12.0,
                    "status": ""
                },
                "6": {
                    "position": 7,
                    "points": 6.0,
                    "status": ""
                },
                "7": {
                    "position": 2,
                    "points": 18.0,
                    "status": ""
                },
                "8": {
                    "position": 7,
                    "points": 6.0,
                    "status": ""
                },
                "9": {
                    "position": 4,
                    "points": 12.0,
                    "status": ""
                },
                "10": {
                    "position": 5,
                    "points": 10.0,
                    "status": ""
                },
                "11": {
                    "position": 2,
                    "points": 18.0,
                    "status": ""
                },
                "12": {
                    "position": 5,
                    "points": 10.0,
                    "status": ""
                },
                "13": {
                    "position": 9,
                    "points": 3.0,
                    "status": ""
                },
                "14": {
                    "position": 2,
                    "points": 18.0,
                    "status": ""
                },
                "15": {
                    "position": 2,
                    "points": 18.0,
                    "status": ""
                },
                "16": {
                    "position": 4,
                    "points": 12.0,
                    "status": ""
                },
                "17": {
                    "position": 6,
                    "points": 8.0,
                    "status": ""
                },
                "18": {
                    "position": 9,
                    "points": 3.0,
                    "status": ""
                }
            },
            "wins": 0,
            "sprint_wins": 0,
            "poles": 0,
            "podiums": 4,
            "fastest_laps": 0,
            "driver_of_the_day": 1
        },
        {
            "driver_id": "thiago",
            "name": "Thiago",
            "number": "",
            "team": "Mercedes",
            "team_id": "team_mercedes",
            "total_points": 165.0,
            "rounds": {
                "1": {
                    "position": 6,
                    "points": 8.0,
                    "status": ""
                },
                "2": {
                    "position": 7,
                    "points": 6.0,
                    "status": ""
                },
                "3": {
                    "position": 5,
                    "points": 10.0,
                    "status": ""
                },
                "4": {
                    "position": 8,
                    "points": 4.0,
                    "status": ""
                },
                "6": {
                    "position": 8,
                    "points": 4.0,
                    "status": ""
                },
                "7": {
                    "position": 5,
                    "points": 10.0,
                    "status": ""
                },
                "8": {
                    "position": 3,
                    "points": 15.0,
                    "status": ""
                },
                "9": {
                    "position": 5,
                    "points": 10.0,
                    "status": ""
                },
                "12": {
                    "position": 3,
                    "points": 15.0,
                    "status": ""
                },
                "13": {
                    "position": 8,
                    "points": 6.0,
                    "status": ""
                },
                "14": {
                    "position": 7,
                    "points": 6.0,
                    "status": ""
                },
                "15": {
                    "position": 1,
                    "points": 25.0,
                    "status": ""
                },
                "16": {
                    "position": 2,
                    "points": 19.0,
                    "status": ""
                },
                "18": {
                    "position": 2,
                    "points": 27.0,
                    "status": ""
                }
            },
            "wins": 1,
            "sprint_wins": 0,
            "poles": 0,
            "podiums": 5,
            "fastest_laps": 1,
            "driver_of_the_day": 1
        },
        {
            "driver_id": "nosoyyo98",
            "name": "NoSoyYo98",
            "number": "",
            "team": "Mercedes",
            "team_id": "team_mercedes",
            "total_points": 155.0,
            "rounds": {
                "2": {
                    "position": 2,
                    "points": 18.0,
                    "status": ""
                },
                "4": {
                    "position": 1,
                    "points": 25.0,
                    "status": ""
                },
                "5": {
                    "position": 2,
                    "points": 19.0,
                    "status": ""
                },
                "6": {
                    "position": 6,
                    "points": 8.0,
                    "status": ""
                },
                "8": {
                    "position": 5,
                    "points": 11.0,
                    "status": ""
                },
                "9": {
                    "position": 1,
                    "points": 26.0,
                    "status": ""
                },
                "12": {
                    "position": 2,
                    "points": 18.0,
                    "status": ""
                },
                "14": {
                    "position": 4,
                    "points": 12.0,
                    "status": ""
                },
                "15": {
                    "position": 4,
                    "points": 12.0,
                    "status": ""
                },
                "18": {
                    "position": 8,
                    "points": 6.0,
                    "status": ""
                }
            },
            "wins": 2,
            "sprint_wins": 0,
            "poles": 0,
            "podiums": 5,
            "fastest_laps": 3,
            "driver_of_the_day": 1
        },
        {
            "driver_id": "capisaurus",
            "name": "Capisaurus",
            "number": "76",
            "team": "Ferrari",
            "team_id": "team_ferrari",
            "total_points": 141.5,
            "rounds": {
                "1": {
                    "position": 7,
                    "points": 6.0,
                    "status": ""
                },
                "2": {
                    "position": 11,
                    "points": 0.0,
                    "status": ""
                },
                "3": {
                    "position": 6,
                    "points": 8.0,
                    "status": ""
                },
                "4": {
                    "position": 10,
                    "points": 1.0,
                    "status": ""
                },
                "5": {
                    "position": 8,
                    "points": 4.0,
                    "status": ""
                },
                "6": {
                    "position": 9,
                    "points": 2.0,
                    "status": ""
                },
                "7": {
                    "position": 7,
                    "points": 6.0,
                    "status": "DNF"
                },
                "8": {
                    "position": 6,
                    "points": 8.0,
                    "status": ""
                },
                "9": {
                    "position": 9,
                    "points": 2.0,
                    "status": ""
                },
                "10": {
                    "position": 7,
                    "points": 6.0,
                    "status": ""
                },
                "11": {
                    "position": 6,
                    "points": 8.0,
                    "status": ""
                },
                "12": {
                    "position": 4,
                    "points": 12.0,
                    "status": ""
                },
                "13": {
                    "position": 6,
                    "points": 12.0,
                    "status": ""
                },
                "14": {
                    "position": 4,
                    "points": 12.0,
                    "status": ""
                },
                "15": {
                    "position": 7,
                    "points": 6.0,
                    "status": ""
                },
                "16": {
                    "position": 6,
                    "points": 8.0,
                    "status": ""
                },
                "17": {
                    "position": 2,
                    "points": 18.0,
                    "status": ""
                },
                "18": {
                    "position": 3,
                    "points": 22.5,
                    "status": ""
                }
            },
            "wins": 0,
            "sprint_wins": 0,
            "poles": 0,
            "podiums": 2,
            "fastest_laps": 0,
            "driver_of_the_day": 0
        },
        {
            "driver_id": "hector_zambrano",
            "name": "Hector Zambrano",
            "number": "",
            "team": "Red Bull",
            "team_id": "team_red_bull",
            "total_points": 120.0,
            "rounds": {
                "1": {
                    "position": 12,
                    "points": 0.0,
                    "status": ""
                },
                "2": {
                    "position": 5,
                    "points": 10.0,
                    "status": ""
                },
                "3": {
                    "position": 7,
                    "points": 6.0,
                    "status": "DNF"
                },
                "4": {
                    "position": 11,
                    "points": 0.0,
                    "status": ""
                },
                "8": {
                    "position": 4,
                    "points": 12.0,
                    "status": ""
                },
                "9": {
                    "position": 8,
                    "points": 4.0,
                    "status": ""
                },
                "10": {
                    "position": 8,
                    "points": 4.0,
                    "status": "DNF"
                },
                "11": {
                    "position": 8,
                    "points": 4.0,
                    "status": ""
                },
                "12": {
                    "position": 6,
                    "points": 8.0,
                    "status": ""
                },
                "13": {
                    "position": 4,
                    "points": 18.0,
                    "status": ""
                },
                "15": {
                    "position": 5,
                    "points": 10.0,
                    "status": ""
                },
                "16": {
                    "position": 5,
                    "points": 10.0,
                    "status": ""
                },
                "17": {
                    "position": 1,
                    "points": 25.0,
                    "status": ""
                },
                "18": {
                    "position": 7,
                    "points": 9.0,
                    "status": ""
                }
            },
            "wins": 1,
            "sprint_wins": 0,
            "poles": 0,
            "podiums": 1,
            "fastest_laps": 0,
            "driver_of_the_day": 0
        },
        {
            "driver_id": "gozark",
            "name": "Gozark",
            "number": "",
            "team": "McLaren",
            "team_id": "team_mclaren",
            "total_points": 99.0,
            "rounds": {
                "1": {
                    "position": 5,
                    "points": 10.0,
                    "status": ""
                },
                "2": {
                    "position": 6,
                    "points": 8.0,
                    "status": ""
                },
                "3": {
                    "position": 1,
                    "points": 26.0,
                    "status": ""
                },
                "5": {
                    "position": 7,
                    "points": 6.0,
                    "status": ""
                },
                "6": {
                    "position": 2,
                    "points": 18.0,
                    "status": ""
                },
                "7": {
                    "position": 8,
                    "points": 4.0,
                    "status": "DNF"
                },
                "10": {
                    "position": 2,
                    "points": 19.0,
                    "status": ""
                },
                "14": {
                    "position": 6,
                    "points": 8.0,
                    "status": ""
                }
            },
            "wins": 1,
            "sprint_wins": 0,
            "poles": 0,
            "podiums": 3,
            "fastest_laps": 2,
            "driver_of_the_day": 1
        },
        {
            "driver_id": "amz_racing",
            "name": "AMZ Racing",
            "number": "",
            "team": "Alpine",
            "team_id": "team_alpine",
            "total_points": 81.0,
            "rounds": {
                "1": {
                    "position": 8,
                    "points": 4.0,
                    "status": ""
                },
                "2": {
                    "position": 1,
                    "points": 26.0,
                    "status": ""
                },
                "5": {
                    "position": 1,
                    "points": 25.0,
                    "status": ""
                },
                "6": {
                    "position": 1,
                    "points": 26.0,
                    "status": ""
                }
            },
            "wins": 3,
            "sprint_wins": 0,
            "poles": 0,
            "podiums": 3,
            "fastest_laps": 2,
            "driver_of_the_day": 1
        },
        {
            "driver_id": "yindaxmx",
            "name": "Yindaxmx",
            "number": "",
            "team": "AlphaTauri",
            "team_id": "team_alphatauri",
            "total_points": 77.0,
            "rounds": {
                "6": {
                    "position": 10,
                    "points": 1.0,
                    "status": ""
                },
                "7": {
                    "position": 6,
                    "points": 8.0,
                    "status": ""
                },
                "9": {
                    "position": 7,
                    "points": 6.0,
                    "status": ""
                },
                "10": {
                    "position": 6,
                    "points": 8.0,
                    "status": ""
                },
                "11": {
                    "position": 7,
                    "points": 6.0,
                    "status": ""
                },
                "12": {
                    "position": 7,
                    "points": 6.0,
                    "status": ""
                },
                "13": {
                    "position": 5,
                    "points": 15.0,
                    "status": ""
                },
                "15": {
                    "position": 8,
                    "points": 4.0,
                    "status": ""
                },
                "16": {
                    "position": 3,
                    "points": 15.0,
                    "status": ""
                },
                "17": {
                    "position": 6,
                    "points": 8.0,
                    "status": ""
                }
            },
            "wins": 0,
            "sprint_wins": 0,
            "poles": 0,
            "podiums": 1,
            "fastest_laps": 0,
            "driver_of_the_day": 0
        },
        {
            "driver_id": "harryh",
            "name": "HarryH",
            "number": "",
            "team": "Reserva",
            "team_id": "team_reserve_driver",
            "total_points": 67.0,
            "rounds": {
                "11": {
                    "position": 4,
                    "points": 12.0,
                    "status": ""
                },
                "12": {
                    "position": 3,
                    "points": 15.0,
                    "status": ""
                },
                "14": {
                    "position": 1,
                    "points": 25.0,
                    "status": ""
                },
                "18": {
                    "position": 5,
                    "points": 15.0,
                    "status": ""
                }
            },
            "wins": 1,
            "sprint_wins": 0,
            "poles": 0,
            "podiums": 2,
            "fastest_laps": 0,
            "driver_of_the_day": 0
        },
        {
            "driver_id": "elgast",
            "name": "ElGast",
            "number": "",
            "team": "Reserva",
            "team_id": "team_reserve_driver",
            "total_points": 52.0,
            "rounds": {
                "11": {
                    "position": 1,
                    "points": 26.0,
                    "status": ""
                },
                "12": {
                    "position": 1,
                    "points": 26.0,
                    "status": ""
                }
            },
            "wins": 2,
            "sprint_wins": 0,
            "poles": 0,
            "podiums": 2,
            "fastest_laps": 2,
            "driver_of_the_day": 0
        },
        {
            "driver_id": "victor_xd",
            "name": "Victor xd",
            "number": "",
            "team": "Alpine",
            "team_id": "team_alpine",
            "total_points": 42.0,
            "rounds": {
                "2": {
                    "position": 12,
                    "points": 0.0,
                    "status": ""
                },
                "3": {
                    "position": 8,
                    "points": 4.0,
                    "status": "DNF"
                },
                "4": {
                    "position": 4,
                    "points": 12.0,
                    "status": ""
                },
                "5": {
                    "position": 5,
                    "points": 10.0,
                    "status": ""
                },
                "6": {
                    "position": 4,
                    "points": 12.0,
                    "status": ""
                },
                "8": {
                    "position": 8,
                    "points": 4.0,
                    "status": ""
                }
            },
            "wins": 0,
            "sprint_wins": 0,
            "poles": 0,
            "podiums": 0,
            "fastest_laps": 0,
            "driver_of_the_day": 0
        },
        {
            "driver_id": "verstappen",
            "name": "Verstappen",
            "number": "",
            "team": "AlphaTauri",
            "team_id": "team_alphatauri",
            "total_points": 32.0,
            "rounds": {
                "1": {
                    "position": 1,
                    "points": 26.0,
                    "status": ""
                },
                "2": {
                    "position": 8,
                    "points": 4.0,
                    "status": ""
                },
                "4": {
                    "position": 9,
                    "points": 2.0,
                    "status": ""
                }
            },
            "wins": 1,
            "sprint_wins": 0,
            "poles": 0,
            "podiums": 1,
            "fastest_laps": 1,
            "driver_of_the_day": 0
        },
        {
            "driver_id": "mrstevehyuga",
            "name": "MrSteveHyuga",
            "number": "",
            "team": "Williams",
            "team_id": "team_williams",
            "total_points": 18.0,
            "rounds": {
                "1": {
                    "position": 13,
                    "points": 0.0,
                    "status": ""
                },
                "9": {
                    "position": 2,
                    "points": 18.0,
                    "status": ""
                }
            },
            "wins": 0,
            "sprint_wins": 0,
            "poles": 0,
            "podiums": 1,
            "fastest_laps": 0,
            "driver_of_the_day": 0
        },
        {
            "driver_id": "chuyto",
            "name": "Chuyto",
            "number": "",
            "team": "Alfa Romeo",
            "team_id": "team_alfa_romeo",
            "total_points": 16.0,
            "rounds": {
                "1": {
                    "position": 9,
                    "points": 2.0,
                    "status": ""
                },
                "2": {
                    "position": 9,
                    "points": 2.0,
                    "status": ""
                },
                "3": {
                    "position": 9,
                    "points": 2.0,
                    "status": "DNF"
                },
                "4": {
                    "position": 6,
                    "points": 8.0,
                    "status": ""
                },
                "5": {
                    "position": 9,
                    "points": 2.0,
                    "status": ""
                },
                "6": {
                    "position": 11,
                    "points": 0.0,
                    "status": ""
                }
            },
            "wins": 0,
            "sprint_wins": 0,
            "poles": 0,
            "podiums": 0,
            "fastest_laps": 0,
            "driver_of_the_day": 0
        },
        {
            "driver_id": "schizain",
            "name": "Schizain",
            "number": "",
            "team": "Reserva",
            "team_id": "team_reserve_driver",
            "total_points": 15.0,
            "rounds": {
                "1": {
                    "position": 3,
                    "points": 15.0,
                    "status": ""
                }
            },
            "wins": 0,
            "sprint_wins": 0,
            "poles": 0,
            "podiums": 1,
            "fastest_laps": 0,
            "driver_of_the_day": 1
        },
        {
            "driver_id": "seb",
            "name": "Seb",
            "number": "",
            "team": "AlphaTauri",
            "team_id": "team_alphatauri",
            "total_points": 12.0,
            "rounds": {
                "8": {
                    "position": 4,
                    "points": 12.0,
                    "status": ""
                }
            },
            "wins": 0,
            "sprint_wins": 0,
            "poles": 0,
            "podiums": 0,
            "fastest_laps": 0,
            "driver_of_the_day": 0
        },
        {
            "driver_id": "antonio_gc",
            "name": "Antonio GC",
            "number": "",
            "team": "Red Bull",
            "team_id": "team_red_bull",
            "total_points": 7.0,
            "rounds": {
                "4": {
                    "position": 7,
                    "points": 7.0,
                    "status": ""
                }
            },
            "wins": 0,
            "sprint_wins": 0,
            "poles": 0,
            "podiums": 0,
            "fastest_laps": 1,
            "driver_of_the_day": 0
        },
        {
            "driver_id": "steelwarrior",
            "name": "SteelWarrior",
            "number": "",
            "team": "McLaren",
            "team_id": "team_mclaren",
            "total_points": 1.0,
            "rounds": {
                "2": {
                    "position": 10,
                    "points": 1.0,
                    "status": ""
                }
            },
            "wins": 0,
            "sprint_wins": 0,
            "poles": 0,
            "podiums": 0,
            "fastest_laps": 0,
            "driver_of_the_day": 0
        },
        {
            "driver_id": "alexmatrix266",
            "name": "AlexMatrix266",
            "number": "",
            "team": "Williams",
            "team_id": "team_williams",
            "total_points": 0.0,
            "rounds": {
                "2": {
                    "position": 11,
                    "points": 0.0,
                    "status": ""
                }
            },
            "wins": 0,
            "sprint_wins": 0,
            "poles": 0,
            "podiums": 0,
            "fastest_laps": 0,
            "driver_of_the_day": 0
        },
        {
            "driver_id": "david",
            "name": "David",
            "number": "",
            "team": "Williams",
            "team_id": "team_williams",
            "total_points": 0.0,
            "rounds": {},
            "wins": 0,
            "sprint_wins": 0,
            "poles": 0,
            "podiums": 0,
            "fastest_laps": 0,
            "driver_of_the_day": 0
        },
        {
            "driver_id": "drasticalrose",
            "name": "Drasticalrose",
            "number": "",
            "team": "Ferrari",
            "team_id": "team_ferrari",
            "total_points": 0.0,
            "rounds": {
                "2": {
                    "position": 14,
                    "points": 0.0,
                    "status": ""
                }
            },
            "wins": 0,
            "sprint_wins": 0,
            "poles": 0,
            "podiums": 0,
            "fastest_laps": 0,
            "driver_of_the_day": 0
        },
        {
            "driver_id": "rubycrayfish",
            "name": "RubyCrayfish",
            "number": "",
            "team": "Ferrari",
            "team_id": "team_ferrari",
            "total_points": 0.0,
            "rounds": {
                "4": {
                    "position": 12,
                    "points": 0.0,
                    "status": ""
                }
            },
            "wins": 0,
            "sprint_wins": 0,
            "poles": 0,
            "podiums": 0,
            "fastest_laps": 0,
            "driver_of_the_day": 0
        }
    ],
    "exported_at": "2026-02-21T19:40:44"
}